fleting/__init__.py
fleting/cli/cli.py
fleting/cli/commands/create.py
fleting/cli/commands/db.py
fleting/cli/commands/delete.py
fleting/cli/commands/info.py
fleting/cli/commands/init.py
fleting/cli/commands/list.py
fleting/cli/commands/run.py
fleting/cli/helpers/project.py
fleting/cli/templates/database.py
fleting/cli/templates/index.py
fleting-1.1.28.dist-info/METADATA
fleting-1.1.28.dist-info/WHEEL
fleting-1.1.28.dist-info/entry_points.txt
fleting-1.1.28.dist-info/licenses/LICENSE
fleting-1.1.28.dist-info/RECORD
