Metadata-Version: 2.4
Name: fleting
Version: 1.1.28
Summary: Micro-framework MVC baseado em Flet para aplicações mobile, tablet e desktop
License: MIT
License-File: LICENSE
Keywords: flet,framework,mvc,ui,desktop,mobile
Author: Alex Yucra
Requires-Python: >=3.11
Classifier: Programming Language :: Python :: 3
Classifier: Programming Language :: Python :: 3.11
Classifier: License :: OSI Approved :: MIT License
Classifier: Operating System :: OS Independent
Requires-Dist: flet
Project-URL: Documentation, https://github.com/alexyucra/fleting/tree/main/docs
Project-URL: Homepage, https://github.com/alexyucra/fleting
Project-URL: Issues, https://github.com/alexyucra/fleting/issues
Project-URL: Repository, https://github.com/alexyucra/fleting
